setup.py
fleader/__init__.py
fleader/fleader.py
fleader/pider.py
fleader/rider.py
fleader/test.py
fleader.egg-info/PKG-INFO
fleader.egg-info/SOURCES.txt
fleader.egg-info/dependency_links.txt
fleader.egg-info/requires.txt
fleader.egg-info/top_level.txt