Metadata-Version: 1.0
Name: fleader
Version: 0.0.12
Summary: Pythonic Http request Library
Home-page: https://github.com/m1coco/Fleader
Author: kele
Author-email: loser7758@qq.com
License: GNU Licence
Keywords: pip,fleader
Platform: any
